{
  "Albania": "AL",
  "Algeria": "DZ",
  "Angola": "AO",
  "Argentina": "AR",
  "Armenia": "AM",
  "Australia": "AU",
  "Austria": "AT",
  "Azerbaijan": "AZ",
  "Bahrain": "BH",
  "Bangladesh": "BD",
  "Belarus": "BY",
  "Belgium": "BE",
  "Benin": "BJ",
  "Bolivia": "BO",
  "Bosnia and Herzegovina": "BA",
  "Botswana": "BW",
  "Brazil": "BR",
  "Brunei Darussalam": "BN",
  "Bulgaria": "BG",
  "Cambodia": "KH",
  "Cameroon": "CM",
  "Canada": "CA",
  "Chile": "CL",
  "China": "CN",
  "Colombia": "CO",
  "Congo": "CG",
  "Costa Rica": "CR",
  "Cote D'ivoire": "CI",
  "Croatia": "HR",
  "Cuba": "CU",
  "Cyprus": "CY",
  "Czech Republic": "CZ",
  "Democratic People's Republic Of": "KP",
  "Denmark": "DK",
  "Dominican Republic": "DO",
  "Ecuador": "EC",
  "Egypt": "EG",
  "El Salvador": "SV",
  "Eritrea": "ER",
  "Estonia": "EE",
  "Ethiopia": "ET",
  "Europe": "EU",
  "Finland": "FI",
  "France": "FR",
  "Gabon": "GA",
  "Georgia": "GE",
  "Germany": "DE",
  "Ghana": "GH",
  "Gibraltar": "GI",
  "Global": "GL",
  "Greece": "GR",
  "Guatemala": "GT",
  "Haiti": "HT",
  "Honduras": "HN",
  "Hong Kong": "HK",
  "Hungary": "HU",
  "Iceland": "IS",
  "India": "IN",
  "Indonesia": "ID",
  "Iran": "IR",
  "Iraq": "IQ",
  "Ireland": "IE",
  "Islamic Republic Of": "AF",
  "Israel": "IL",
  "Italy": "IT",
  "Jamaica": "JM",
  "Japan": "JP",
  "Jordan": "JO",
  "Kazakhstan": "KZ",
  "Kenya": "KE",
  "Korea": "KP",
  "Kuwait": "KW",
  "Kyrgyzstan": "KG",
  "Latvia": "LV",
  "Lebanon": "LB",
  "Libyan Arab Jamahiriya": "LY",
  "Lithuania": "LT",
  "Luxembourg": "LU",
  "Macedonia": "MK",
  "Malaysia": "MY",
  "Malta": "MT",
  "Mexico": "MX",
  "Moldova": "MD",
  "Mongolia": "MN",
  "Morocco": "MA",
  "Mozambique": "MZ",
  "Myanmar": "MM",
  "Namibia": "NA",
  "Nepal": "NP",
  "Netherlands": "NL",
  "Netherlands Antilles": "AN",
  "New Zealand": "NZ",
  "Nicaragua": "NI",
  "Nigeria": "NG",
  "Norway": "NO",
  "Oman": "OM",
  "Pakistan": "PK",
  "Panama": "PA",
  "Paraguay": "PY",
  "Peru": "PE",
  "Philippines": "PH",
  "Poland": "PL",
  "Portugal": "PT",
  "Province Of China": "TW",
  "Qatar": "QA",
  "Republic Of": "AL",
  "Romania": "RO",
  "Russian Federation": "RU",
  "Saudi Arabia": "SA",
  "Senegal": "SN",
  "Serbie": "RS",
  "Singapore": "SG",
  "Slovakia": "SK",
  "Slovenia": "SI",
  "South Africa": "ZA",
  "Spain": "ES",
  "Sri Lanka": "LK",
  "Sudan": "SD",
  "Sweden": "SE",
  "Switzerland": "CH",
  "Syrian Arab Republic": "SY",
  "Taiwan": "TW",
  "Tajikistan": "TJ",
  "Tanzania": "TZ",
  "Thailand": "TH",
  "The Democratic Republic Of The": "CD",
  "The Former Yugoslav Republic Of": "UN",
  "Togo": "TG",
  "Trinidad and Tobago": "TT",
  "Tunisia": "TN",
  "Turkey": "TR",
  "Turkmenistan": "TM",
  "Ukraine": "UA",
  "United Arab Emirates": "AE",
  "United Kingdom": "GB",
  "United Republic Of": "TZ",
  "United States": "US",
  "Uruguay": "UY",
  "Uzbekistan": "UZ",
  "Venezuela": "VE",
  "Vietnam": "VN",
  "Yemen": "YE",
  "Zambia": "ZM",
  "Zimbabwe": "ZW"
}